swt/__init__.py
"swt/__init__.py,cover"
swt-0.2.0.dist-info/LICENSE
swt-0.2.0.dist-info/WHEEL
swt-0.2.0.dist-info/METADATA
swt-0.2.0.dist-info/RECORD
